{
  "users": [
    {
      "id": "1",
      "email": "test@gmail.com",
      "password": "password123"
    },
    {
      "id": "2",
      "email": "abc@gmail.com",
      "password": "pass123"
    },
    {
      "id": "3546",
      "email": "test2@gmail.com",
      "password": "pass123"
    },
    {
      "id": "9074",
      "email": "test3@gmail.com",
      "password": "password1234"
    },
    {
      "id": "8ca3",
      "email": "test4@gmail.com",
      "password": "password1234@"
    },
    {
      "id": "cec4",
      "email": "mamoni.debolina@gmail.com",
      "password": "Vidyasagar"
    },
    {
      "id": "8c24",
      "email": "bornini@gmail.com",
      "password": "pass123$"
    }
  ]
}